fiftyone_pipeline_engines_fiftyone/__init__.py
fiftyone_pipeline_engines_fiftyone/share_usage.py
fiftyone_pipeline_engines_fiftyone/share_usage_evidencekeyfilter.py
fiftyone_pipeline_engines_fiftyone/share_usage_tracker.py
fiftyone_pipeline_engines_fiftyone-4.5.3.dist-info/METADATA
fiftyone_pipeline_engines_fiftyone-4.5.3.dist-info/WHEEL
fiftyone_pipeline_engines_fiftyone-4.5.3.dist-info/top_level.txt
fiftyone_pipeline_engines_fiftyone-4.5.3.dist-info/RECORD
