Metadata-Version: 2.4
Name: fiftyone_pipeline_engines_fiftyone
Version: 4.5.3
Summary: The 51Degrees Pipeline API is a generic web request intelligence and data processing solution with the ability to add a range of 51Degrees and/or custom plug ins (Engines). It includes a ShareUsage engine that sends usage data to 51Degrees in zipped batches.
Home-page: https://51degrees.com/
Author: 51Degrees Engineering
Author-email: engineering@51degrees.com
License: EUPL-1.2
Classifier: Development Status :: 5 - Production/Stable
Classifier: Programming Language :: Python
Classifier: License :: OSI Approved :: European Union Public Licence 1.2 (EUPL 1.2)
Classifier: Operating System :: OS Independent
Classifier: Topic :: Software Development :: Libraries :: Python Modules
Requires-Python: >=3.8
Requires-Dist: fiftyone_pipeline_engines
Requires-Dist: requests
Requires-Dist: cachetools
Provides-Extra: testing
Requires-Dist: flask; extra == "testing"
Dynamic: author
Dynamic: author-email
Dynamic: classifier
Dynamic: description
Dynamic: description-content-type
Dynamic: home-page
Dynamic: license
Dynamic: provides-extra
Dynamic: requires-dist
Dynamic: requires-python
Dynamic: summary
